osam_yoloworld/__init__.py
osam_yoloworld/_models.py
osam_yoloworld/clip/LICENSE
osam_yoloworld/clip/__init__.py
osam_yoloworld/clip/bpe_simple_vocab_16e6.txt.gz
osam_yoloworld/clip/clip.py
osam_yoloworld/clip/simple_tokenizer.py
osam_yoloworld-0.1.0.dist-info/METADATA
osam_yoloworld-0.1.0.dist-info/WHEEL
osam_yoloworld-0.1.0.dist-info/licenses/LICENSE
osam_yoloworld-0.1.0.dist-info/RECORD
